dash_stylish_header_footer_hook/__init__.py
dash_stylish_header_footer_hook/header.py
dash_stylish_header_footer_hook-0.0.3.dist-info/METADATA
dash_stylish_header_footer_hook-0.0.3.dist-info/WHEEL
dash_stylish_header_footer_hook-0.0.3.dist-info/entry_points.txt
dash_stylish_header_footer_hook-0.0.3.dist-info/top_level.txt
dash_stylish_header_footer_hook-0.0.3.dist-info/RECORD
