Metadata-Version: 2.4
Name: dash_stylish_header_footer_hook
Version: 0.0.3
Summary: Stylish header and footer components for Dash applications using Dash Hooks
Home-page: https://github.com/banana0000/dash_stylish_header_footer_hook
Author: koveszter
Author-email: Eszter <koveszter7@gmail.com>
Requires-Python: >=3.8
Requires-Dist: dash>=3.0.0
Provides-Extra: dev
Requires-Dist: pytest>=6.0; extra == "dev"
Requires-Dist: ruff>=0.11.0; extra == "dev"
Dynamic: author
Dynamic: home-page
